LICENSE
MANIFEST.in
README.md
setup.py
negar_gui/Ui_hwin.py
negar_gui/Ui_mwin.py
negar_gui/Ui_uwin.py
negar_gui/__init__.py
negar_gui/constants.py
negar_gui/gui.py
negar_gui/main.py
negar_gui/resource_rc.py
negar_gui/style.qss
negar_gui/tempCodeRunnerFile.py
negar_gui.egg-info/PKG-INFO
negar_gui.egg-info/SOURCES.txt
negar_gui.egg-info/dependency_links.txt
negar_gui.egg-info/entry_points.txt
negar_gui.egg-info/requires.txt
negar_gui.egg-info/top_level.txt
negar_gui/icons/logo.ico
negar_gui/icons/logo.png
negar_gui/ts/fa.qm