Metadata-Version: 2.4
Name: negar-gui
Version: 0.9.11
Summary: Graphical User Interface for Negar -- Persian Text Editor
Home-page: http://github.com/javadr/negar-gui
Author: Javad Razavian
Author-email: javadr@gmail.com
License: GPLv3
Keywords: Spellcheck Persian Text-Editor
Requires-Python: >=3.8
License-File: LICENSE
Requires-Dist: python-negar>=1.3
Requires-Dist: PyQt6
Requires-Dist: pyperclip
Requires-Dist: pyuca
Requires-Dist: redlines
Requires-Dist: regex
Requires-Dist: requests
Requires-Dist: qrcode
Requires-Dist: docopt
Requires-Dist: Image
Requires-Dist: pyqtdarktheme
Requires-Dist: toml
Dynamic: author
Dynamic: author-email
Dynamic: description
Dynamic: description-content-type
Dynamic: home-page
Dynamic: keywords
Dynamic: license
Dynamic: license-file
Dynamic: requires-dist
Dynamic: requires-python
Dynamic: summary
